cc_my_utils/__init__.py
cc_my_utils/convert_time.py
cc_my_utils/get_time.py
cc_my_utils-0.0.5.dist-info/METADATA
cc_my_utils-0.0.5.dist-info/WHEEL
cc_my_utils-0.0.5.dist-info/top_level.txt
cc_my_utils-0.0.5.dist-info/RECORD
