Metadata-Version: 2.1
Name: cc-my-utils
Version: 0.0.5
Summary: my utils
Home-page: https://github.com/houm01/cc-utils
